{
	"LoginUser" : [{
		"UserId":"userID002",
		"Password":"userPW002"
	}],
	
	"CheckUserIdDupl" : [{
		"UserId" : "userID002"
	}],
	
	"InsertUser" : [{
		"UserId" : "userID002",
		"Name" : "김유정",
		"Password" : "userPW002",
		"Email" : "test@gmail.com"
	}],

	"UpdateUser": [{
		"UserId" : "userID002",
		"newPW" : "changedPW002"
	}],
	
	"DeleteUser":[{
		"UserId" : "userID002",
		"Password": "tempPW002"
	}],
	
	"findID" : [{
		"Email" : "test@gmail.com"
	}],
	
	"findPW" : [{
		"UserId" : "userID002",
		"Email" : "test@gmail.com"
	}]
}